buf/__init__.py
buf/validate/__init__.py
buf/validate/validate_pb2.py
buf/validate/validate_pb2.pyi
buf/validate/validate_pb2_grpc.py
grpc_client_wrapper_kessel/__init__.py
grpc_client_wrapper_kessel/client.py
kessel/__init__.py
kessel/relations/__init__.py
kessel/relations/v1beta1/__init__.py
kessel/relations/v1beta1/check_pb2.py
kessel/relations/v1beta1/check_pb2.pyi
kessel/relations/v1beta1/check_pb2_grpc.py
kessel/relations/v1beta1/common_pb2.py
kessel/relations/v1beta1/common_pb2.pyi
kessel/relations/v1beta1/common_pb2_grpc.py
kessel/relations/v1beta1/lookup_pb2.py
kessel/relations/v1beta1/lookup_pb2.pyi
kessel/relations/v1beta1/lookup_pb2_grpc.py
kessel/relations/v1beta1/relation_tuples_pb2.py
kessel/relations/v1beta1/relation_tuples_pb2.pyi
kessel/relations/v1beta1/relation_tuples_pb2_grpc.py
relations_grpc_clients_python_kessel_project-0.3.10.dist-info/licenses/LICENSE
relations_grpc_clients_python_kessel_project-0.3.10.dist-info/METADATA
relations_grpc_clients_python_kessel_project-0.3.10.dist-info/WHEEL
relations_grpc_clients_python_kessel_project-0.3.10.dist-info/top_level.txt
relations_grpc_clients_python_kessel_project-0.3.10.dist-info/RECORD
