Metadata-Version: 2.4
Name: relations-grpc-clients-python-kessel-project
Version: 0.3.10
Summary: This package contains grpc python clients based on kessel relations-api.
Home-page: https://github.com/project-kessel
Author: Libor Pichler
Author-email: "Libor Pichler" <lpichler@redhat.com>
License: Apache-2.0
Classifier: License :: OSI Approved :: Apache Software License
Classifier: Programming Language :: Python
Classifier: Programming Language :: Python :: 3.9
Classifier: Operating System :: OS Independent
Requires-Python: >=3.9
License-File: LICENSE
Requires-Dist: grpcio
Requires-Dist: grpcio-tools
Requires-Dist: protobuf
Requires-Dist: googleapis-common-protos
Dynamic: license-file
